ro_legal_fl/__init__.py
ro_legal_fl/meta.json
ro_legal_fl/ro_legal_fl-3.6.1/README.md
ro_legal_fl/ro_legal_fl-3.6.1/config.cfg
ro_legal_fl/ro_legal_fl-3.6.1/meta.json
ro_legal_fl/ro_legal_fl-3.6.1/tokenizer
ro_legal_fl/ro_legal_fl-3.6.1/attribute_ruler/patterns
ro_legal_fl/ro_legal_fl-3.6.1/lemmatizer/cfg
ro_legal_fl/ro_legal_fl-3.6.1/lemmatizer/model
ro_legal_fl/ro_legal_fl-3.6.1/lemmatizer/trees
ro_legal_fl/ro_legal_fl-3.6.1/morphologizer/cfg
ro_legal_fl/ro_legal_fl-3.6.1/morphologizer/model
ro_legal_fl/ro_legal_fl-3.6.1/ner/cfg
ro_legal_fl/ro_legal_fl-3.6.1/ner/model
ro_legal_fl/ro_legal_fl-3.6.1/ner/moves
ro_legal_fl/ro_legal_fl-3.6.1/parser/cfg
ro_legal_fl/ro_legal_fl-3.6.1/parser/model
ro_legal_fl/ro_legal_fl-3.6.1/parser/moves
ro_legal_fl/ro_legal_fl-3.6.1/tagger/cfg
ro_legal_fl/ro_legal_fl-3.6.1/tagger/model
ro_legal_fl/ro_legal_fl-3.6.1/tok2vec/cfg
ro_legal_fl/ro_legal_fl-3.6.1/tok2vec/model
ro_legal_fl/ro_legal_fl-3.6.1/vocab/key2row
ro_legal_fl/ro_legal_fl-3.6.1/vocab/lookups.bin
ro_legal_fl/ro_legal_fl-3.6.1/vocab/strings.json
ro_legal_fl/ro_legal_fl-3.6.1/vocab/vectors
ro_legal_fl/ro_legal_fl-3.6.1/vocab/vectors.cfg
ro_legal_fl-3.6.1.dist-info/LICENSE
ro_legal_fl-3.6.1.dist-info/METADATA
ro_legal_fl-3.6.1.dist-info/WHEEL
ro_legal_fl-3.6.1.dist-info/entry_points.txt
ro_legal_fl-3.6.1.dist-info/top_level.txt
ro_legal_fl-3.6.1.dist-info/RECORD
