Metadata-Version: 2.1
Name: ro-legal-fl
Version: 3.6.1
Summary: A Spacy Package for Legal Document Processing & Other Resources
Home-page: https://github.com/senisioi/rolegal
Author: Sergiu Nisioi
Author-email: sergiu.nisioi@unibuc.ro
License: CC4R https://constantvzw.org/wefts/cc4r.en.html
Platform: UNKNOWN
License-File: LICENSE
Requires-Dist: spacy (<3.7.0,>=3.6.1)
